CHANGES.rst
CONTRIBUTORS.rst
MANIFEST.in
README.rst
setup.cfg
setup.py
docs/LICENSE.GPL
docs/LICENSE.txt
src/interlegis/__init__.py
src/interlegis.intranetmodelo.policy.egg-info/PKG-INFO
src/interlegis.intranetmodelo.policy.egg-info/SOURCES.txt
src/interlegis.intranetmodelo.policy.egg-info/dependency_links.txt
src/interlegis.intranetmodelo.policy.egg-info/namespace_packages.txt
src/interlegis.intranetmodelo.policy.egg-info/not-zip-safe
src/interlegis.intranetmodelo.policy.egg-info/requires.txt
src/interlegis.intranetmodelo.policy.egg-info/top_level.txt
src/interlegis/intranetmodelo/__init__.py
src/interlegis/intranetmodelo/policy/__init__.py
src/interlegis/intranetmodelo/policy/adapters.py
src/interlegis/intranetmodelo/policy/config.py
src/interlegis/intranetmodelo/policy/configure.zcml
src/interlegis/intranetmodelo/policy/cover.py
src/interlegis/intranetmodelo/policy/interfaces.py
src/interlegis/intranetmodelo/policy/overrides.zcml
src/interlegis/intranetmodelo/policy/profiles.zcml
src/interlegis/intranetmodelo/policy/setuphandlers.py
src/interlegis/intranetmodelo/policy/testing.py
src/interlegis/intranetmodelo/policy/userdataschema.py
src/interlegis/intranetmodelo/policy/utils.py
src/interlegis/intranetmodelo/policy/Extensions/Install.py
src/interlegis/intranetmodelo/policy/Extensions/__init__.py
src/interlegis/intranetmodelo/policy/browser/__init__.py
src/interlegis/intranetmodelo/policy/browser/members.py
src/interlegis/intranetmodelo/policy/browser/templates/members_list_view.pt
src/interlegis/intranetmodelo/policy/locales/interlegis.intranetmodelo.policy.pot
src/interlegis/intranetmodelo/policy/locales/manual.pot
src/interlegis/intranetmodelo/policy/locales/plone.pot
src/interlegis/intranetmodelo/policy/locales/pt_BR/LC_MESSAGES/interlegis.intranetmodelo.policy.po
src/interlegis/intranetmodelo/policy/locales/pt_BR/LC_MESSAGES/plone.po
src/interlegis/intranetmodelo/policy/profiles/default/browserlayer.xml
src/interlegis/intranetmodelo/policy/profiles/default/componentregistry.xml
src/interlegis/intranetmodelo/policy/profiles/default/import_steps.xml
src/interlegis/intranetmodelo/policy/profiles/default/interlegis.intranetmodelo.policy.txt
src/interlegis/intranetmodelo/policy/profiles/default/memberdata_properties.xml
src/interlegis/intranetmodelo/policy/profiles/default/metadata.xml
src/interlegis/intranetmodelo/policy/profiles/default/portlets.xml
